interfacy_web/__init__.py
interfacy_web/auto_element.py
interfacy_web/class_element.py
interfacy_web/draggable_element.py
interfacy_web/elements.py
interfacy_web/file_picker.py
interfacy_web/icons.py
interfacy_web/parser.py
interfacy_web/pydantic_element.py
interfacy_web/util.py
interfacy_web-0.0.2.dist-info/LICENSE
interfacy_web-0.0.2.dist-info/METADATA
interfacy_web-0.0.2.dist-info/WHEEL
interfacy_web-0.0.2.dist-info/top_level.txt
interfacy_web-0.0.2.dist-info/RECORD
