Metadata-Version: 2.1
Name: interfacy-web
Version: 0.0.2
Author-email: Žiga Ivanšek <ziga.ivansek@gmail.com>
Project-URL: Repository, https://github.com/zigai/interfacy-web
Classifier: Intended Audience :: Developers
Classifier: License :: OSI Approved :: MIT License
Classifier: Operating System :: OS Independent
Classifier: Programming Language :: Python
Classifier: Programming Language :: Python :: 3.10
Classifier: Programming Language :: Python :: 3 :: Only
Classifier: Topic :: Software Development :: Libraries :: Python Modules
Requires-Python: >=3.10
License-File: LICENSE
Requires-Dist: stdl ==0.4.8
Requires-Dist: strto ==0.1.2
Requires-Dist: objinspect ==0.2.6
Requires-Dist: pydantic ==2.4.2
Requires-Dist: loguru >=0.7.2
Requires-Dist: nicegui >=1.4.0
Provides-Extra: dev
Requires-Dist: black ; extra == 'dev'
Requires-Dist: pytest ; extra == 'dev'
Requires-Dist: flake8 ; extra == 'dev'
Provides-Extra: test
Requires-Dist: pytest ; extra == 'test'
